autotrainer/training/__init__.py
autotrainer/training/event_slot.py
autotrainer/training/training_action.py
autotrainer/training/training_phase.py
autotrainer/training/training_plan.py
autotrainer/training/training_predicate.py
autotrainer/training/training_progress.py
autotrainer/training/training_protocols.py
autotrainer/training/training_simulator.py
auto_trainer_training-0.9.9.dist-info/METADATA
auto_trainer_training-0.9.9.dist-info/WHEEL
auto_trainer_training-0.9.9.dist-info/RECORD
