Metadata-Version: 2.4
Name: auto-trainer-training
Version: 0.9.9
Summary: Training protocol objects and implementations for Mouse-GYM autotrainer
License: AGPL-3.0-only
Classifier: Operating System :: OS Independent
Classifier: Programming Language :: Python :: 3
Requires-Python: >=3.8
Requires-Dist: pyhumps==3.8.0
Requires-Dist: transitions==0.9.2
Provides-Extra: test
Requires-Dist: pytest==8.2.0; extra == 'test'
Provides-Extra: tools
Requires-Dist: pywebview==6.0; extra == 'tools'
